examples/__init__.py
gptlite/__init__.py
gptlite/types.py
gptlite/utils/__init__.py
gptlite/utils/chunk.py
gptlite/utils/convert.py
gptlite-0.0.5.dist-info/LICENSE
gptlite-0.0.5.dist-info/METADATA
gptlite-0.0.5.dist-info/WHEEL
gptlite-0.0.5.dist-info/top_level.txt
gptlite-0.0.5.dist-info/RECORD
