Metadata-Version: 2.1
Name: gptlite
Version: 0.0.5
Summary: GPTLite by LLMApp Group
Home-page: https://github.com/llmapp/gptlite/
Author: llmapp
License-File: LICENSE
Requires-Dist: langchain-core
Requires-Dist: openai
Requires-Dist: python-dotenv
Requires-Dist: types-PyYAML
Provides-Extra: test
Requires-Dist: pytest; extra == "test"
Requires-Dist: coverage; extra == "test"
Requires-Dist: flake8; extra == "test"
Requires-Dist: black; extra == "test"
Requires-Dist: isort; extra == "test"
Requires-Dist: pytest-cov; extra == "test"
Requires-Dist: mypy; extra == "test"
Requires-Dist: gitchangelog; extra == "test"
Requires-Dist: mkdocs; extra == "test"
Requires-Dist: langchain-core; extra == "test"
